teleoprtc/__init__.py
teleoprtc/builder.py
teleoprtc/info.py
teleoprtc/stream.py
teleoprtc/tracks.py
teleoprtc-1.0.3.dist-info/LICENSE
teleoprtc-1.0.3.dist-info/METADATA
teleoprtc-1.0.3.dist-info/WHEEL
teleoprtc-1.0.3.dist-info/top_level.txt
teleoprtc-1.0.3.dist-info/RECORD
