Metadata-Version: 2.1
Name: teleoprtc
Version: 1.0.3
Summary: Comma webRTC abstractions
Author-email: Vehicle Researcher <user@comma.ai>
License: MIT License
Project-URL: Homepage, https://github.com/commaai/teleoprtc
Project-URL: Bug Tracker, https://github.com/commaai/teleoprtc/issues
Classifier: Programming Language :: Python :: 3
Classifier: License :: OSI Approved :: MIT License
Classifier: Operating System :: OS Independent
Requires-Python: >=3.8
License-File: LICENSE
Requires-Dist: aiortc >=1.6.0
Requires-Dist: aiohttp >=3.7.0
Requires-Dist: av <13.0.0,>=11.0.0
Requires-Dist: numpy >=1.19.0
Provides-Extra: dev
Requires-Dist: parameterized >=0.8 ; extra == 'dev'
Requires-Dist: pre-commit ; extra == 'dev'
